cloudsmith_cli/__init__.py
cloudsmith_cli/__main__.py
cloudsmith_cli/cli/__init__.py
cloudsmith_cli/cli/command.py
cloudsmith_cli/cli/config.py
cloudsmith_cli/cli/decorators.py
cloudsmith_cli/cli/exceptions.py
cloudsmith_cli/cli/saml.py
cloudsmith_cli/cli/table.py
cloudsmith_cli/cli/types.py
cloudsmith_cli/cli/utils.py
cloudsmith_cli/cli/validators.py
cloudsmith_cli/cli/webserver.py
cloudsmith_cli/cli/commands/__init__.py
cloudsmith_cli/cli/commands/auth.py
cloudsmith_cli/cli/commands/check.py
cloudsmith_cli/cli/commands/copy.py
cloudsmith_cli/cli/commands/delete.py
cloudsmith_cli/cli/commands/dependencies.py
cloudsmith_cli/cli/commands/docs.py
cloudsmith_cli/cli/commands/download.py
cloudsmith_cli/cli/commands/entitlements.py
cloudsmith_cli/cli/commands/help_.py
cloudsmith_cli/cli/commands/list_.py
cloudsmith_cli/cli/commands/login.py
cloudsmith_cli/cli/commands/main.py
cloudsmith_cli/cli/commands/move.py
cloudsmith_cli/cli/commands/push.py
cloudsmith_cli/cli/commands/quarantine.py
cloudsmith_cli/cli/commands/repos.py
cloudsmith_cli/cli/commands/resync.py
cloudsmith_cli/cli/commands/status.py
cloudsmith_cli/cli/commands/tags.py
cloudsmith_cli/cli/commands/tokens.py
cloudsmith_cli/cli/commands/upstream.py
cloudsmith_cli/cli/commands/whoami.py
cloudsmith_cli/cli/commands/metrics/__init__.py
cloudsmith_cli/cli/commands/metrics/command.py
cloudsmith_cli/cli/commands/metrics/entitlements.py
cloudsmith_cli/cli/commands/metrics/packages.py
cloudsmith_cli/cli/commands/policy/__init__.py
cloudsmith_cli/cli/commands/policy/command.py
cloudsmith_cli/cli/commands/policy/deny.py
cloudsmith_cli/cli/commands/policy/license.py
cloudsmith_cli/cli/commands/policy/vulnerability.py
cloudsmith_cli/cli/commands/quota/__init__.py
cloudsmith_cli/cli/commands/quota/command.py
cloudsmith_cli/cli/commands/quota/history.py
cloudsmith_cli/cli/commands/quota/quota.py
cloudsmith_cli/cli/tests/__init__.py
cloudsmith_cli/cli/tests/conftest.py
cloudsmith_cli/cli/tests/test_push.py
cloudsmith_cli-1.11.1.dist-info/licenses/LICENSE
cloudsmith_cli-1.11.1.dist-info/METADATA
cloudsmith_cli-1.11.1.dist-info/WHEEL
cloudsmith_cli-1.11.1.dist-info/entry_points.txt
cloudsmith_cli-1.11.1.dist-info/top_level.txt
cloudsmith_cli-1.11.1.dist-info/RECORD
