Metadata-Version: 2.4
Name: cloudsmith-cli
Version: 1.11.1
Summary: Cloudsmith Command-Line Interface (CLI)
Home-page: https://github.com/cloudsmith-io/cloudsmith-cli
Author: Cloudsmith Ltd
Author-email: support@cloudsmith.io
License: Apache License 2.0
Keywords: cloudsmith,cli,devops
Platform: any
Classifier: Development Status :: 5 - Production/Stable
Classifier: Environment :: Console
Classifier: Intended Audience :: Developers
Classifier: Intended Audience :: System Administrators
Classifier: License :: OSI Approved :: Apache Software License
Classifier: Operating System :: POSIX :: Linux
Classifier: Programming Language :: Python
Classifier: Programming Language :: Python :: 3.9
Classifier: Programming Language :: Python :: 3.10
Classifier: Programming Language :: Python :: 3.11
Classifier: Programming Language :: Python :: 3.12
Classifier: Programming Language :: Python :: 3.13
Classifier: Programming Language :: Python :: 3.14
Classifier: Topic :: Internet
Classifier: Topic :: System :: Systems Administration
Classifier: Topic :: Utilities
Requires-Python: >=3.9.0
License-File: LICENSE
Requires-Dist: click!=8.3.0,>=8.1.8
Requires-Dist: click-configfile>=0.2.3
Requires-Dist: click-didyoumean>=0.0.3
Requires-Dist: click-spinner>=0.1.7
Requires-Dist: cloudsmith-api<3.0,>=2.0.22
Requires-Dist: keyring>=25.4.1
Requires-Dist: requests>=2.18.4
Requires-Dist: requests_toolbelt>=1.0.0
Requires-Dist: semver>=2.7.9
Requires-Dist: urllib3>=2.5
Dynamic: author
Dynamic: author-email
Dynamic: classifier
Dynamic: description
Dynamic: description-content-type
Dynamic: home-page
Dynamic: keywords
Dynamic: license
Dynamic: license-file
Dynamic: platform
Dynamic: requires-dist
Dynamic: requires-python
Dynamic: summary
